nonebot_plugin_awsmgmt/__init__.py
nonebot_plugin_awsmgmt/config.py
nonebot_plugin_awsmgmt/cost_explorer_manager.py
nonebot_plugin_awsmgmt/ec2_manager.py
nonebot_plugin_awsmgmt/lightsail_manager.py
nonebot_plugin_awsmgmt/schedule_manager.py
nonebot_plugin_awsmgmt-0.1.3.dist-info/METADATA
nonebot_plugin_awsmgmt-0.1.3.dist-info/WHEEL
nonebot_plugin_awsmgmt-0.1.3.dist-info/RECORD
