Metadata-Version: 2.3
Name: nonebot-plugin-awsmgmt
Version: 0.1.3
Summary: A nonebot2 plugin for managing AWS EC2, Lightsail, and Cost Explorer via commands.
Author-email: Maximilian Wu <me@maxng.cc>
Requires-Python: >=3.8
Requires-Dist: aioboto3>=15.0.0
Requires-Dist: nonebot-plugin-apscheduler>=0.4.0
Requires-Dist: nonebot2>=2.4.2
